CS230 DLDCA/verilog/23b1041_lab2_q1q2/rca_Nbit.v
module half_adder(a, b, S, c);
input a,b;
output S;
output c;

assign S=a^b;
assign c=a&b;
endmodule


module full_adder(a, b, cin, S, c);
input a,b,cin;
output S,c;



wire carry_1,carry_2;
wire sum_1;

half_adder ha1(.a(a),.b(b),.S(sum_1),.c(carry_1));
half_adder ha2(.a(sum_1),.b(cin),.S(S),.c(carry_2));

assign c=carry_1|carry_2;





endmodule

module rca_Nbit #(parameter N = 32) (a, b, cin, S, c);
input [N-1:0]a,b;
input cin;
output [N-1:0] S;
output c;
wire [N:0] co;
assign co[0]=cin;
generate
    genvar i;
    for(i=0;i<N;i=i+1)
        begin
         full_adder fi(.a(a[i]),.b(b[i]),.cin(co[i]),.S(S[i]),.c(co[i+1]));
        end
    endgenerate
   assign c=co[N];
endmodule

CS230 DLDCA/verilog/23b1041_lab2_q1q2/tb_rca_32bit.v
`timescale 1ns/1ps

module tb_rca_32_bit;

parameter N = 32;

// declare your signals as reg or wire
reg [N-1:0] a,b;
reg cin;


wire  [N-1:0] S;
wire c;

rca_Nbit #(.N(N)) dut  (.a(a), .b(b), .cin(cin), .S(S), .c(c));

initial begin	
// write the stimuli conditions


a=32'b00000000000000000000000000000000;
b=32'b00000000000000000000000000000000;
cin=1'b0;
end

always #2 b= b+4'b1011;
always #3 a=a+4'b1100;
always #10 cin=~cin;

initial 
begin

$monitor("a=%d,b=%d,cin=%b,S=%d,c=%b",a,b,cin,S,c);
end
initial
begin
#200 $finish;
end


initial begin
    $dumpfile("rca_32bit.vcd");
    $dumpvars(0, tb_rca_32_bit);
end

endmodule

CS230 DLDCA/verilog/23b1041_lab2_q1q2/rca_32bit.vcd
$date
	Mon Aug 19 01:32:40 2024
$end
$version
	Icarus Verilog
$end
$timescale
	1ps
$end
$scope module tb_rca_32_bit $end
$var wire 1 ! c $end
$var wire 32 " S [31:0] $end
$var reg 32 # a [31:0] $end
$var reg 32 $ b [31:0] $end
$var reg 1 % cin $end
$scope module dut $end
$var wire 32 & a [31:0] $end
$var wire 32 ' b [31:0] $end
$var wire 1 % cin $end
$var wire 33 ( co [32:0] $end
$var wire 1 ! c $end
$var wire 32 ) S [31:0] $end
$scope begin genblk1[0] $end
$scope module fi $end
$var wire 1 * a $end
$var wire 1 + b $end
$var wire 1 , c $end
$var wire 1 - cin $end
$var wire 1 . sum_1 $end
$var wire 1 / carry_2 $end
$var wire 1 0 carry_1 $end
$var wire 1 1 S $end
$scope module ha1 $end
$var wire 1 . S $end
$var wire 1 * a $end
$var wire 1 + b $end
$var wire 1 0 c $end
$upscope $end
$scope module ha2 $end
$var wire 1 1 S $end
$var wire 1 . a $end
$var wire 1 - b $end
$var wire 1 / c $end
$upscope $end
$upscope $end
$upscope $end
$scope begin genblk1[1] $end
$scope module fi $end
$var wire 1 2 a $end
$var wire 1 3 b $end
$var wire 1 4 c $end
$var wire 1 5 cin $end
$var wire 1 6 sum_1 $end
$var wire 1 7 carry_2 $end
$var wire 1 8 carry_1 $end
$var wire 1 9 S $end
$scope module ha1 $end
$var wire 1 6 S $end
$var wire 1 2 a $end
$var wire 1 3 b $end
$var wire 1 8 c $end
$upscope $end
$scope module ha2 $end
$var wire 1 9 S $end
$var wire 1 6 a $end
$var wire 1 5 b $end
$var wire 1 7 c $end
$upscope $end
$upscope $end
$upscope $end
$scope begin genblk1[2] $end
$scope module fi $end
$var wire 1 : a $end
$var wire 1 ; b $end
$var wire 1 < c $end
$var wire 1 = cin $end
$var wire 1 > sum_1 $end
$var wire 1 ? carry_2 $end
$var wire 1 @ carry_1 $end
$var wire 1 A S $end
$scope module ha1 $end
$var wire 1 > S $end
$var wire 1 : a $end
$var wire 1 ; b $end
$var wire 1 @ c $end
$upscope $end
$scope module ha2 $end
$var wire 1 A S $end
$var wire 1 > a $end
$var wire 1 = b $end
$var wire 1 ? c $end
$upscope $end
$upscope $end
$upscope $end
$scope begin genblk1[3] $end
$scope module fi $end
$var wire 1 B a $end
$var wire 1 C b $end
$var wire 1 D c $end
$var wire 1 E cin $end
$var wire 1 F sum_1 $end
$var wire 1 G carry_2 $end
$var wire 1 H carry_1 $end
$var wire 1 I S $end
$scope module ha1 $end
$var wire 1 F S $end
$var wire 1 B a $end
$var wire 1 C b $end
$var wire 1 H c $end
$upscope $end
$scope module ha2 $end
$var wire 1 I S $end
$var wire 1 F a $end
$var wire 1 E b $end
$var wire 1 G c $end
$upscope $end
$upscope $end
$upscope $end
$scope begin genblk1[4] $end
$scope module fi $end
$var wire 1 J a $end
$var wire 1 K b $end
$var wire 1 L c $end
$var wire 1 M cin $end
$var wire 1 N sum_1 $end
$var wire 1 O carry_2 $end
$var wire 1 P carry_1 $end
$var wire 1 Q S $end
$scope module ha1 $end
$var wire 1 N S $end
$var wire 1 J a $end
$var wire 1 K b $end
$var wire 1 P c $end
$upscope $end
$scope module ha2 $end
$var wire 1 Q S $end
$var wire 1 N a $end
$var wire 1 M b $end
$var wire 1 O c $end
$upscope $end
$upscope $end
$upscope $end
$scope begin genblk1[5] $end
$scope module fi $end
$var wire 1 R a $end
$var wire 1 S b $end
$var wire 1 T c $end
$var wire 1 U cin $end
$var wire 1 V sum_1 $end
$var wire 1 W carry_2 $end
$var wire 1 X carry_1 $end
$var wire 1 Y S $end
$scope module ha1 $end
$var wire 1 V S $end
$var wire 1 R a $end
$var wire 1 S b $end
$var wire 1 X c $end
$upscope $end
$scope module ha2 $end
$var wire 1 Y S $end
$var wire 1 V a $end
$var wire 1 U b $end
$var wire 1 W c $end
$upscope $end
$upscope $end
$upscope $end
$scope begin genblk1[6] $end
$scope module fi $end
$var wire 1 Z a $end
$var wire 1 [ b $end
$var wire 1 \ c $end
$var wire 1 ] cin $end
$var wire 1 ^ sum_1 $end
$var wire 1 _ carry_2 $end
$var wire 1 ` carry_1 $end
$var wire 1 a S $end
$scope module ha1 $end
$var wire 1 ^ S $end
$var wire 1 Z a $end
$var wire 1 [ b $end
$var wire 1 ` c $end
$upscope $end
$scope module ha2 $end
$var wire 1 a S $end
$var wire 1 ^ a $end
$var wire 1 ] b $end
$var wire 1 _ c $end
$upscope $end
$upscope $end
$upscope $end
$scope begin genblk1[7] $end
$scope module fi $end
$var wire 1 b a $end
$var wire 1 c b $end
$var wire 1 d c $end
$var wire 1 e cin $end
$var wire 1 f sum_1 $end
$var wire 1 g carry_2 $end
$var wire 1 h carry_1 $end
$var wire 1 i S $end
$scope module ha1 $end
$var wire 1 f S $end
$var wire 1 b a $end
$var wire 1 c b $end
$var wire 1 h c $end
$upscope $end
$scope module ha2 $end
$var wire 1 i S $end
$var wire 1 f a $end
$var wire 1 e b $end
$var wire 1 g c $end
$upscope $end
$upscope $end
$upscope $end
$scope begin genblk1[8] $end
$scope module fi $end
$var wire 1 j a $end
$var wire 1 k b $end
$var wire 1 l c $end
$var wire 1 m cin $end
$var wire 1 n sum_1 $end
$var wire 1 o carry_2 $end
$var wire 1 p carry_1 $end
$var wire 1 q S $end
$scope module ha1 $end
$var wire 1 n S $end
$var wire 1 j a $end
$var wire 1 k b $end
$var wire 1 p c $end
$upscope $end
$scope module ha2 $end
$var wire 1 q S $end
$var wire 1 n a $end
$var wire 1 m b $end
$var wire 1 o c $end
$upscope $end
$upscope $end
$upscope $end
$scope begin genblk1[9] $end
$scope module fi $end
$var wire 1 r a $end
$var wire 1 s b $end
$var wire 1 t c $end
$var wire 1 u cin $end
$var wire 1 v sum_1 $end
$var wire 1 w carry_2 $end
$var wire 1 x carry_1 $end
$var wire 1 y S $end
$scope module ha1 $end
$var wire 1 v S $end
$var wire 1 r a $end
$var wire 1 s b $end
$var wire 1 x c $end
$upscope $end
$scope module ha2 $end
$var wire 1 y S $end
$var wire 1 v a $end
$var wire 1 u b $end
$var wire 1 w c $end
$upscope $end
$upscope $end
$upscope $end
$scope begin genblk1[10] $end
$scope module fi $end
$var wire 1 z a $end
$var wire 1 { b $end
$var wire 1 | c $end
$var wire 1 } cin $end
$var wire 1 ~ sum_1 $end
$var wire 1 !" carry_2 $end
$var wire 1 "" carry_1 $end
$var wire 1 #" S $end
$scope module ha1 $end
$var wire 1 ~ S $end
$var wire 1 z a $end
$var wire 1 { b $end
$var wire 1 "" c $end
$upscope $end
$scope module ha2 $end
$var wire 1 #" S $end
$var wire 1 ~ a $end
$var wire 1 } b $end
$var wire 1 !" c $end
$upscope $end
$upscope $end
$upscope $end
$scope begin genblk1[11] $end
$scope module fi $end
$var wire 1 $" a $end
$var wire 1 %" b $end
$var wire 1 &" c $end
$var wire 1 '" cin $end
$var wire 1 (" sum_1 $end
$var wire 1 )" carry_2 $end
$var wire 1 *" carry_1 $end
$var wire 1 +" S $end
$scope module ha1 $end
$var wire 1 (" S $end
$var wire 1 $" a $end
$var wire 1 %" b $end
$var wire 1 *" c $end
$upscope $end
$scope module ha2 $end
$var wire 1 +" S $end
$var wire 1 (" a $end
$var wire 1 '" b $end
$var wire 1 )" c $end
$upscope $end
$upscope $end
$upscope $end
$scope begin genblk1[12] $end
$scope module fi $end
$var wire 1 ," a $end
$var wire 1 -" b $end
$var wire 1 ." c $end
$var wire 1 /" cin $end
$var wire 1 0" sum_1 $end
$var wire 1 1" carry_2 $end
$var wire 1 2" carry_1 $end
$var wire 1 3" S $end
$scope module ha1 $end
$var wire 1 0" S $end
$var wire 1 ," a $end
$var wire 1 -" b $end
$var wire 1 2" c $end
$upscope $end
$scope module ha2 $end
$var wire 1 3" S $end
$var wire 1 0" a $end
$var wire 1 /" b $end
$var wire 1 1" c $end
$upscope $end
$upscope $end
$upscope $end
$scope begin genblk1[13] $end
$scope module fi $end
$var wire 1 4" a $end
$var wire 1 5" b $end
$var wire 1 6" c $end
$var wire 1 7" cin $end
$var wire 1 8" sum_1 $end
$var wire 1 9" carry_2 $end
$var wire 1 :" carry_1 $end
$var wire 1 ;" S $end
$scope module ha1 $end
$var wire 1 8" S $end
$var wire 1 4" a $end
$var wire 1 5" b $end
$var wire 1 :" c $end
$upscope $end
$scope module ha2 $end
$var wire 1 ;" S $end
$var wire 1 8" a $end
$var wire 1 7" b $end
$var wire 1 9" c $end
$upscope $end
$upscope $end
$upscope $end
$scope begin genblk1[14] $end
$scope module fi $end
$var wire 1 <" a $end
$var wire 1 =" b $end
$var wire 1 >" c $end
$var wire 1 ?" cin $end
$var wire 1 @" sum_1 $end
$var wire 1 A" carry_2 $end
$var wire 1 B" carry_1 $end
$var wire 1 C" S $end
$scope module ha1 $end
$var wire 1 @" S $end
$var wire 1 <" a $end
$var wire 1 =" b $end
$var wire 1 B" c $end
$upscope $end
$scope module ha2 $end
$var wire 1 C" S $end
$var wire 1 @" a $end
$var wire 1 ?" b $end
$var wire 1 A" c $end
$upscope $end
$upscope $end
$upscope $end
$scope begin genblk1[15] $end
$scope module fi $end
$var wire 1 D" a $end
$var wire 1 E" b $end
$var wire 1 F" c $end
$var wire 1 G" cin $end
$var wire 1 H" sum_1 $end
$var wire 1 I" carry_2 $end
$var wire 1 J" carry_1 $end
$var wire 1 K" S $end
$scope module ha1 $end
$var wire 1 H" S $end
$var wire 1 D" a $end
$var wire 1 E" b $end
$var wire 1 J" c $end
$upscope $end
$scope module ha2 $end
$var wire 1 K" S $end
$var wire 1 H" a $end
$var wire 1 G" b $end
$var wire 1 I" c $end
$upscope $end
$upscope $end
$upscope $end
$scope begin genblk1[16] $end
$scope module fi $end
$var wire 1 L" a $end
$var wire 1 M" b $end
$var wire 1 N" c $end
$var wire 1 O" cin $end
$var wire 1 P" sum_1 $end
$var wire 1 Q" carry_2 $end
$var wire 1 R" carry_1 $end
$var wire 1 S" S $end
$scope module ha1 $end
$var wire 1 P" S $end
$var wire 1 L" a $end
$var wire 1 M" b $end
$var wire 1 R" c $end
$upscope $end
$scope module ha2 $end
$var wire 1 S" S $end
$var wire 1 P" a $end
$var wire 1 O" b $end
$var wire 1 Q" c $end
$upscope $end
$upscope $end
$upscope $end
$scope begin genblk1[17] $end
$scope module fi $end
$var wire 1 T" a $end
$var wire 1 U" b $end
$var wire 1 V" c $end
$var wire 1 W" cin $end
$var wire 1 X" sum_1 $end
$var wire 1 Y" carry_2 $end
$var wire 1 Z" carry_1 $end
$var wire 1 [" S $end
$scope module ha1 $end
$var wire 1 X" S $end
$var wire 1 T" a $end
$var wire 1 U" b $end
$var wire 1 Z" c $end
$upscope $end
$scope module ha2 $end
$var wire 1 [" S $end
$var wire 1 X" a $end
$var wire 1 W" b $end
$var wire 1 Y" c $end
$upscope $end
$upscope $end
$upscope $end
$scope begin genblk1[18] $end
$scope module fi $end
$var wire 1 \" a $end
$var wire 1 ]" b $end
$var wire 1 ^" c $end
$var wire 1 _" cin $end
$var wire 1 `" sum_1 $end
$var wire 1 a" carry_2 $end
$var wire 1 b" carry_1 $end
$var wire 1 c" S $end
$scope module ha1 $end
$var wire 1 `" S $end
$var wire 1 \" a $end
$var wire 1 ]" b $end
$var wire 1 b" c $end
$upscope $end
$scope module ha2 $end
$var wire 1 c" S $end
$var wire 1 `" a $end
$var wire 1 _" b $end
$var wire 1 a" c $end
$upscope $end
$upscope $end
$upscope $end
$scope begin genblk1[19] $end
$scope module fi $end
$var wire 1 d" a $end
$var wire 1 e" b $end
$var wire 1 f" c $end
$var wire 1 g" cin $end
$var wire 1 h" sum_1 $end
$var wire 1 i" carry_2 $end
$var wire 1 j" carry_1 $end
$var wire 1 k" S $end
$scope module ha1 $end
$var wire 1 h" S $end
$var wire 1 d" a $end
$var wire 1 e" b $end
$var wire 1 j" c $end
$upscope $end
$scope module ha2 $end
$var wire 1 k" S $end
$var wire 1 h" a $end
$var wire 1 g" b $end
$var wire 1 i" c $end
$upscope $end
$upscope $end
$upscope $end
$scope begin genblk1[20] $end
$scope module fi $end
$var wire 1 l" a $end
$var wire 1 m" b $end
$var wire 1 n" c $end
$var wire 1 o" cin $end
$var wire 1 p" sum_1 $end
$var wire 1 q" carry_2 $end
$var wire 1 r" carry_1 $end
$var wire 1 s" S $end
$scope module ha1 $end
$var wire 1 p" S $end
$var wire 1 l" a $end
$var wire 1 m" b $end
$var wire 1 r" c $end
$upscope $end
$scope module ha2 $end
$var wire 1 s" S $end
$var wire 1 p" a $end
$var wire 1 o" b $end
$var wire 1 q" c $end
$upscope $end
$upscope $end
$upscope $end
$scope begin genblk1[21] $end
$scope module fi $end
$var wire 1 t" a $end
$var wire 1 u" b $end
$var wire 1 v" c $end
$var wire 1 w" cin $end
$var wire 1 x" sum_1 $end
$var wire 1 y" carry_2 $end
$var wire 1 z" carry_1 $end
$var wire 1 {" S $end
$scope module ha1 $end
$var wire 1 x" S $end
$var wire 1 t" a $end
$var wire 1 u" b $end
$var wire 1 z" c $end
$upscope $end
$scope module ha2 $end
$var wire 1 {" S $end
$var wire 1 x" a $end
$var wire 1 w" b $end
$var wire 1 y" c $end
$upscope $end
$upscope $end
$upscope $end
$scope begin genblk1[22] $end
$scope module fi $end
$var wire 1 |" a $end
$var wire 1 }" b $end
$var wire 1 ~" c $end
$var wire 1 !# cin $end
$var wire 1 "# sum_1 $end
$var wire 1 ## carry_2 $end
$var wire 1 $# carry_1 $end
$var wire 1 %# S $end
$scope module ha1 $end
$var wire 1 "# S $end
$var wire 1 |" a $end
$var wire 1 }" b $end
$var wire 1 $# c $end
$upscope $end
$scope module ha2 $end
$var wire 1 %# S $end
$var wire 1 "# a $end
$var wire 1 !# b $end
$var wire 1 ## c $end
$upscope $end
$upscope $end
$upscope $end
$scope begin genblk1[23] $end
$scope module fi $end
$var wire 1 &# a $end
$var wire 1 '# b $end
$var wire 1 (# c $end
$var wire 1 )# cin $end
$var wire 1 *# sum_1 $end
$var wire 1 +# carry_2 $end
$var wire 1 ,# carry_1 $end
$var wire 1 -# S $end
$scope module ha1 $end
$var wire 1 *# S $end
$var wire 1 &# a $end
$var wire 1 '# b $end
$var wire 1 ,# c $end
$upscope $end
$scope module ha2 $end
$var wire 1 -# S $end
$var wire 1 *# a $end
$var wire 1 )# b $end
$var wire 1 +# c $end
$upscope $end
$upscope $end
$upscope $end
$scope begin genblk1[24] $end
$scope module fi $end
$var wire 1 .# a $end
$var wire 1 /# b $end
$var wire 1 0# c $end
$var wire 1 1# cin $end
$var wire 1 2# sum_1 $end
$var wire 1 3# carry_2 $end
$var wire 1 4# carry_1 $end
$var wire 1 5# S $end
$scope module ha1 $end
$var wire 1 2# S $end
$var wire 1 .# a $end
$var wire 1 /# b $end
$var wire 1 4# c $end
$upscope $end
$scope module ha2 $end
$var wire 1 5# S $end
$var wire 1 2# a $end
$var wire 1 1# b $end
$var wire 1 3# c $end
$upscope $end
$upscope $end
$upscope $end
$scope begin genblk1[25] $end
$scope module fi $end
$var wire 1 6# a $end
$var wire 1 7# b $end
$var wire 1 8# c $end
$var wire 1 9# cin $end
$var wire 1 :# sum_1 $end
$var wire 1 ;# carry_2 $end
$var wire 1 <# carry_1 $end
$var wire 1 =# S $end
$scope module ha1 $end
$var wire 1 :# S $end
$var wire 1 6# a $end
$var wire 1 7# b $end
$var wire 1 <# c $end
$upscope $end
$scope module ha2 $end
$var wire 1 =# S $end
$var wire 1 :# a $end
$var wire 1 9# b $end
$var wire 1 ;# c $end
$upscope $end
$upscope $end
$upscope $end
$scope begin genblk1[26] $end
$scope module fi $end
$var wire 1 ># a $end
$var wire 1 ?# b $end
$var wire 1 @# c $end
$var wire 1 A# cin $end
$var wire 1 B# sum_1 $end
$var wire 1 C# carry_2 $end
$var wire 1 D# carry_1 $end
$var wire 1 E# S $end
$scope module ha1 $end
$var wire 1 B# S $end
$var wire 1 ># a $end
$var wire 1 ?# b $end
$var wire 1 D# c $end
$upscope $end
$scope module ha2 $end
$var wire 1 E# S $end
$var wire 1 B# a $end
$var wire 1 A# b $end
$var wire 1 C# c $end
$upscope $end
$upscope $end
$upscope $end
$scope begin genblk1[27] $end
$scope module fi $end
$var wire 1 F# a $end
$var wire 1 G# b $end
$var wire 1 H# c $end
$var wire 1 I# cin $end
$var wire 1 J# sum_1 $end
$var wire 1 K# carry_2 $end
$var wire 1 L# carry_1 $end
$var wire 1 M# S $end
$scope module ha1 $end
$var wire 1 J# S $end
$var wire 1 F# a $end
$var wire 1 G# b $end
$var wire 1 L# c $end
$upscope $end
$scope module ha2 $end
$var wire 1 M# S $end
$var wire 1 J# a $end
$var wire 1 I# b $end
$var wire 1 K# c $end
$upscope $end
$upscope $end
$upscope $end
$scope begin genblk1[28] $end
$scope module fi $end
$var wire 1 N# a $end
$var wire 1 O# b $end
$var wire 1 P# c $end
$var wire 1 Q# cin $end
$var wire 1 R# sum_1 $end
$var wire 1 S# carry_2 $end
$var wire 1 T# carry_1 $end
$var wire 1 U# S $end
$scope module ha1 $end
$var wire 1 R# S $end
$var wire 1 N# a $end
$var wire 1 O# b $end
$var wire 1 T# c $end
$upscope $end
$scope module ha2 $end
$var wire 1 U# S $end
$var wire 1 R# a $end
$var wire 1 Q# b $end
$var wire 1 S# c $end
$upscope $end
$upscope $end
$upscope $end
$scope begin genblk1[29] $end
$scope module fi $end
$var wire 1 V# a $end
$var wire 1 W# b $end
$var wire 1 X# c $end
$var wire 1 Y# cin $end
$var wire 1 Z# sum_1 $end
$var wire 1 [# carry_2 $end
$var wire 1 \# carry_1 $end
$var wire 1 ]# S $end
$scope module ha1 $end
$var wire 1 Z# S $end
$var wire 1 V# a $end
$var wire 1 W# b $end
$var wire 1 \# c $end
$upscope $end
$scope module ha2 $end
$var wire 1 ]# S $end
$var wire 1 Z# a $end
$var wire 1 Y# b $end
$var wire 1 [# c $end
$upscope $end
$upscope $end
$upscope $end
$scope begin genblk1[30] $end
$scope module fi $end
$var wire 1 ^# a $end
$var wire 1 _# b $end
$var wire 1 `# c $end
$var wire 1 a# cin $end
$var wire 1 b# sum_1 $end
$var wire 1 c# carry_2 $end
$var wire 1 d# carry_1 $end
$var wire 1 e# S $end
$scope module ha1 $end
$var wire 1 b# S $end
$var wire 1 ^# a $end
$var wire 1 _# b $end
$var wire 1 d# c $end
$upscope $end
$scope module ha2 $end
$var wire 1 e# S $end
$var wire 1 b# a $end
$var wire 1 a# b $end
$var wire 1 c# c $end
$upscope $end
$upscope $end
$upscope $end
$scope begin genblk1[31] $end
$scope module fi $end
$var wire 1 f# a $end
$var wire 1 g# b $end
$var wire 1 h# c $end
$var wire 1 i# cin $end
$var wire 1 j# sum_1 $end
$var wire 1 k# carry_2 $end
$var wire 1 l# carry_1 $end
$var wire 1 m# S $end
$scope module ha1 $end
$var wire 1 j# S $end
$var wire 1 f# a $end
$var wire 1 g# b $end
$var wire 1 l# c $end
$upscope $end
$scope module ha2 $end
$var wire 1 m# S $end
$var wire 1 j# a $end
$var wire 1 i# b $end
$var wire 1 k# c $end
$upscope $end
$upscope $end
$upscope $end
$upscope $end
$upscope $end
$enddefinitions $end
#0
$dumpvars
0m#
0l#
0k#
0j#
0i#
0h#
0g#
0f#
0e#
0d#
0c#
0b#
0a#
0`#
0_#
0^#
0]#
0\#
0[#
0Z#
0Y#
0X#
0W#
0V#
0U#
0T#
0S#
0R#
0Q#
0P#
0O#
0N#
0M#
0L#
0K#
0J#
0I#
0H#
0G#
0F#
0E#
0D#
0C#
0B#
0A#
0@#
0?#
0>#
0=#
0<#
0;#
0:#
09#
08#
07#
06#
05#
04#
03#
02#
01#
00#
0/#
0.#
0-#
0,#
0+#
0*#
0)#
0(#
0'#
0&#
0%#
0$#
0##
0"#
0!#
0~"
0}"
0|"
0{"
0z"
0y"
0x"
0w"
0v"
0u"
0t"
0s"
0r"
0q"
0p"
0o"
0n"
0m"
0l"
0k"
0j"
0i"
0h"
0g"
0f"
0e"
0d"
0c"
0b"
0a"
0`"
0_"
0^"
0]"
0\"
0["
0Z"
0Y"
0X"
0W"
0V"
0U"
0T"
0S"
0R"
0Q"
0P"
0O"
0N"
0M"
0L"
0K"
0J"
0I"
0H"
0G"
0F"
0E"
0D"
0C"
0B"
0A"
0@"
0?"
0>"
0="
0<"
0;"
0:"
09"
08"
07"
06"
05"
04"
03"
02"
01"
00"
0/"
0."
0-"
0,"
0+"
0*"
0)"
0("
0'"
0&"
0%"
0$"
0#"
0""
0!"
0~
0}
0|
0{
0z
0y
0x
0w
0v
0u
0t
0s
0r
0q
0p
0o
0n
0m
0l
0k
0j
0i
0h
0g
0f
0e
0d
0c
0b
0a
0`
0_
0^
0]
0\
0[
0Z
0Y
0X
0W
0V
0U
0T
0S
0R
0Q
0P
0O
0N
0M
0L
0K
0J
0I
0H
0G
0F
0E
0D
0C
0B
0A
0@
0?
0>
0=
0<
0;
0:
09
08
07
06
05
04
03
02
01
00
0/
0.
0-
0,
0+
0*
b0 )
b0 (
b0 '
b0 &
0%
b0 $
b0 #
b0 "
0!
$end
#2000
11
19
b1011 "
b1011 )
1I
1.
16
1F
1+
13
1C
b1011 $
b1011 '
#3000
1Q
1M
1A
b10111 "
b10111 )
0I
b10000 (
1D
1>
0F
1H
1:
1B
b1100 #
b1100 &
#4000
1Y
1G
1U
1E
1M
1L
01
0A
1<
0I
b111000 (
1D
b100010 "
b100010 )
0Q
1O
0.
0>
1@
1F
0H
1N
0+
1;
0C
1K
b10110 $
b10110 '
#6000
0U
0L
1Q
0O
0M
0a
0D
0]
1I
0G
0T
0E
11
09
b111001 "
b111001 )
1Y
0W
b0 (
0<
1.
06
1V
0@
1+
03
0;
0K
1S
0:
1J
b100001 $
b100001 '
b11000 #
b11000 &
#8000
1a
1]
1T
0Y
1W
1U
1L
0Q
1O
1M
01
1A
b1000100 "
b1000100 )
0I
b1110000 (
1D
0.
1>
0F
1H
0+
1;
1C
b101100 $
b101100 '
#9000
1G
0U
1E
1M
0L
0A
1<
0I
b1011000 (
1D
1Q
0O
b1010000 "
b1010000 )
0Y
0W
0>
1@
1F
0H
0N
0V
1X
1:
0B
0J
1R
b100100 #
b100100 &
#10000
1A
1=
14
17
0Y
15
0M
0U
1,
0D
0L
1/
09
1I
0G
1Q
0O
1.
16
0F
1N
b1011100 "
b1011100 )
01
1+
13
0C
1K
1-
b110111 $
b110111 '
b1001111 (
1%
#12000
0A
0=
04
19
07
0i
05
0e
0I
0,
0]
0\
0E
11
0/
1Y
0T
b1110011 "
b1110011 )
1a
0_
b1 (
0<
0.
1V
0X
1^
0@
0+
0;
0K
0S
1[
0:
1J
b1000010 $
b1000010 '
b110000 #
b110000 &
#14000
15
b11 (
1,
01
1/
19
1A
b1111110 "
b1111110 )
1I
1.
06
1>
1F
1+
03
1;
1C
b1001101 $
b1001101 '
#15000
1i
1e
1\
0a
1_
1]
1T
0Y
1W
1U
1L
0Q
1O
1E
1M
0A
1<
b10001010 "
b10001010 )
1I
b11111011 (
1D
0>
1@
0F
1H
1:
1B
b111100 #
b111100 &
#16000
09
05
0I
0,
0E
11
0/
1A
b11110001 (
0<
b10010101 "
b10010101 )
1Q
0O
0.
1>
0@
0N
1P
0+
0;
1K
b1011000 $
b1011000 '
#18000
1=
14
0]
17
0T
15
0Q
1Y
0W
1,
0M
0U
01
1/
09
1I
0D
1A
b10000111 (
0L
b10101100 "
b10101100 )
0a
0_
1.
16
1F
0H
0>
0P
0^
1`
1+
13
0C
0K
1S
0:
0J
0R
1Z
b1100011 $
b1100011 '
b1001000 #
b1001000 &
#20000
0=
04
0E
1Q
19
07
0<
1M
05
1A
0?
0I
1D
0,
0.
1>
0F
1H
b10110110 "
b10110110 )
01
0/
0+
1;
1C
0-
b1101110 $
b1101110 '
b10010000 (
0%
#21000
1a
1]
1T
0Y
1W
1G
1U
1E
1M
1L
0A
1<
0I
b11111000 (
1D
b11000010 "
b11000010 )
0Q
1O
0>
1@
1F
0H
1N
1:
0B
1J
b1010100 #
b1010100 &
#22000
0M
0D
1I
0G
0E
11
09
1A
b11100000 (
0<
b11001101 "
b11001101 )
0Q
0O
1.
06
1>
0@
0N
1P
1+
03
0;
1K
b1111001 $
b1111001 '
#24000
0]
0q
0T
0m
1Y
0W
0e
0d
0U
01
0I
1a
0_
0\
b11100100 "
b11100100 )
1i
0g
b0 (
0L
0.
0F
1^
0`
1f
0P
0+
1;
0C
0K
0S
0[
1c
0:
0J
1R
b10000100 $
b10000100 '
b1100000 #
b1100000 &
#26000
11
19
b11101111 "
b11101111 )
1I
1.
16
1F
1+
13
1C
b10001111 $
b10001111 '
#27000
1Q
1E
1M
0A
1<
b11111011 "
b11111011 )
1I
b11000 (
1D
0>
1@
0F
1H
1:
1B
b1101100 #
b1101100 &
#28000
1q
1m
1d
0i
1g
1e
1\
0a
1_
1]
1T
0Y
1W
0I
1U
0E
1L
01
1A
b111110000 (
0<
b100000110 "
b100000110 )
0Q
1O
0.
1>
0@
1N
0+
0;
1K
b10011010 $
b10011010 '
#30000
0U
0L
15
1Q
0O
1,
0M
1/
19
1I
0D
0Y
0W
1.
06
1F
0H
0V
1X
b100011110 "
b100011110 )
01
1+
03
1;
0C
0K
1S
0:
1J
1-
b10100101 $
b10100101 '
b1111000 #
b1111000 &
b111000011 (
1%
#32000
09
05
1Y
0,
1U
11
0/
0A
b100101001 "
b100101001 )
0Q
b111100001 (
1L
0.
0>
0N
1P
0+
0;
1K
b10110000 $
b10110000 '
#33000
0e
0U
0]
0\
1A
0I
1Q
0L
1Y
0W
b100000001 (
0T
0a
0_
b100110101 "
b100110101 )
0i
0g
1>
0F
1N
0P
1V
0X
0^
0f
1h
1:
0B
0J
0R
0Z
1b
b10000100 #
b10000100 &
#34000
1a
1]
1T
0Y
1W
1U
1L
0Q
1O
1M
1D
1G
1E
1<
0A
1?
1=
14
17
15
b101111111 (
1,
01
1/
09
b101000000 "
b101000000 )
0I
1.
16
1F
1+
13
1C
b10111011 $
b10111011 '
#36000
0E
0<
1A
0?
0=
0U
04
0L
19
07
1Q
0O
0i
05
0M
0]
0e
0,
0D
0T
b100000001 (
0\
11
0/
0I
0G
0Y
0W
b101010111 "
b101010111 )
1a
0_
0.
0F
0V
1^
0+
1;
0C
0K
0S
1[
0:
1J
b11000110 $
b11000110 '
b10010000 #
b10010000 &
#38000
15
1Y
1,
1U
01
1/
19
0A
b101100010 "
b101100010 )
0Q
b100100011 (
1L
1.
06
0>
0N
1P
1+
03
0;
1K
b11010001 $
b11010001 '
#39000
1A
b101101110 "
b101101110 )
1I
1>
1F
1:
1B
b10011100 #
b10011100 &
#40000
1Q
09
1E
1M
05
0A
1<
1I
1D
0,
0.
0>
1@
0F
1H
b101111000 "
b101111000 )
01
0/
0+
1;
1C
0-
b11011100 $
b11011100 '
b100111000 (
0%
#42000
1i
1e
1\
0Q
0Y
0a
1_
0M
0E
0U
1]
11
19
1I
0G
0D
b110001111 "
b110001111 )
1A
0<
0L
b111000000 (
1T
1.
16
1F
0H
1>
0@
0P
1X
1+
13
0C
0K
1S
0:
0J
1R
b11100111 $
b11100111 '
b10101000 #
b10101000 &
#44000
01
0A
b110011010 "
b110011010 )
1Q
0.
0>
1N
0+
0;
1K
b11110010 $
b11110010 '
#45000
1Y
1U
1A
0I
b110100110 "
b110100110 )
0Q
b111100000 (
1L
1>
0F
0N
1P
1:
0B
1J
b10110100 #
b10110100 &
#46000
1Q
1M
1D
1G
1E
11
09
0A
b111111000 (
1<
b110110001 "
b110110001 )
0I
1.
06
0>
1@
1F
1+
03
1;
1C
b11111101 $
b11111101 '
#48000
0Q
0M
0e
0y
0D
0\
0u
1I
0G
0Y
1a
0_
0m
0l
0E
0U
0]
01
1i
0g
0d
b111001000 "
b111001000 )
1q
0o
0<
0L
b0 (
0T
0.
1f
0h
1n
0@
0P
0X
0+
0;
0K
0S
0[
0c
1k
0:
0J
0R
1Z
b100001000 $
b100001000 '
b11000000 #
b11000000 &
